pinterest_cli/__init__.py
pinterest_cli/cli_parser.py
pinterest_cli/downloader.py
pinterest_cli/driver_installer.py
pinterest_cli/io.py
pinterest_cli/main.py
pinterest_cli/manifest.json
pinterest_cli/scraper.py
pinterest_cli/utils.py
scrape_img/__init__.py
scrape_img/cli_parser.py
scrape_img/downloader.py
scrape_img/driver_installer.py
scrape_img/io.py
scrape_img/main.py
scrape_img/manifest.json
scrape_img/scraper.py
scrape_img/utils.py
pinterest_cli-0.0.8.dist-info/LICENSE
pinterest_cli-0.0.8.dist-info/METADATA
pinterest_cli-0.0.8.dist-info/WHEEL
pinterest_cli-0.0.8.dist-info/entry_points.txt
pinterest_cli-0.0.8.dist-info/top_level.txt
pinterest_cli-0.0.8.dist-info/RECORD
