Metadata-Version: 2.1
Name: pinterest-cli
Version: 0.0.8
Summary: CLI tool to scrape images from Pinterest url
Home-page: https://github.com/sean1832/pinterest-cli
Author: Zeke Zhang
License: Apache-2.0
Classifier: Development Status :: 1 - Planning
Classifier: Intended Audience :: Developers
Classifier: License :: OSI Approved :: Apache Software License
Classifier: Programming Language :: Python
Classifier: Programming Language :: Python :: 3.10
Classifier: Programming Language :: Python :: 3.11
Classifier: Programming Language :: Python :: 3.12
Classifier: Environment :: Console
Classifier: Operating System :: Microsoft :: Windows
License-File: LICENSE
Requires-Dist: selenium >=4.9.0
Requires-Dist: pillow >=10.1.0
